structuralglass/__init__.py
structuralglass/demands.py
structuralglass/equiv_thick_models.py
structuralglass/glass_types.py
structuralglass/helpers.py
structuralglass/layers.py
structuralglass/resources/__init__.py
structuralglass/resources/unit_def.txt
structuralglass-0.0.3.dist-info/LICENSE
structuralglass-0.0.3.dist-info/METADATA
structuralglass-0.0.3.dist-info/WHEEL
structuralglass-0.0.3.dist-info/top_level.txt
structuralglass-0.0.3.dist-info/RECORD
