Metadata-Version: 2.1
Name: structuralglass
Version: 0.0.3
Summary: A python package for structural glass analysis.
Author-email: Norman JN Richardson <normanrichardson@gmail.com>
Project-URL: Repository, https://github.com/normanrichardson/structuralglass
Project-URL: Documentation, https://structuralglass.readthedocs.io/en/latest/index.html
Project-URL: Bug Tracker, https://github.com/normanrichardson/structuralglass/issues
Classifier: Programming Language :: Python :: 3
Classifier: License :: OSI Approved :: MIT License
Classifier: Operating System :: OS Independent
Requires-Python: >=3.8
License-File: LICENSE
Requires-Dist: pint
Requires-Dist: scipy
Requires-Dist: numpy
Provides-Extra: dev
Requires-Dist: pint ==0.20 ; extra == 'dev'
Requires-Dist: scipy ==1.12.0 ; extra == 'dev'
Requires-Dist: numpy ==1.26.4 ; extra == 'dev'
Requires-Dist: Sphinx ; extra == 'dev'
Requires-Dist: sphinx-rtd-theme ; extra == 'dev'
Requires-Dist: black ; extra == 'dev'
Requires-Dist: isort ; extra == 'dev'
Requires-Dist: flake8 ; extra == 'dev'
Provides-Extra: dist
Requires-Dist: twine ; extra == 'dist'
Requires-Dist: build ; extra == 'dist'
